this_person_does_not_exist_but_has_age_and_gender/__init__.py
this_person_does_not_exist_but_has_age_and_gender/this_person_does_not_exist_but_has_age_and_gender.py
this_person_does_not_exist_but_has_age_and_gender-1.0.0.dist-info/LICENSE
this_person_does_not_exist_but_has_age_and_gender-1.0.0.dist-info/METADATA
this_person_does_not_exist_but_has_age_and_gender-1.0.0.dist-info/WHEEL
this_person_does_not_exist_but_has_age_and_gender-1.0.0.dist-info/top_level.txt
this_person_does_not_exist_but_has_age_and_gender-1.0.0.dist-info/RECORD
