Metadata-Version: 2.1
Name: this-person-does-not-exist-but-has-age-and-gender
Version: 1.0.0
Summary: Get the person with right gender and age
Home-page: https://github.com/DorianKucharski/ThisPersonDoesNotExistButHasAgeAndGender
Author: Dorian Kucharski
Author-email: dorian.kucharski1@gmail.com
License: UNKNOWN
Platform: UNKNOWN
Classifier: Programming Language :: Python :: 3
Classifier: License :: OSI Approved :: MIT License
Classifier: Operating System :: OS Independent
Requires-Python: >=3.6
Requires-Dist: cv2
